antigravity/__init__.py
calliope_mini/__init__.py
calliope_mini/accelerometer.py
calliope_mini/button.py
calliope_mini/display.py
calliope_mini/gyrometer.py
calliope_mini/i2c.py
calliope_mini/image.py
calliope_mini/led.py
calliope_mini/magnetometer.py
calliope_mini/pin.py
calliope_mini/pin_instances.py
calliope_mini/sensor.py
calliope_mini/spi.py
calliope_mini/toplevel_functions.py
calliope_mini/uart.py
love/__init__.py
music/__init__.py
os/__init__.py
radio/__init__.py
random/__init__.py
this/__init__.py
utime/__init__.py
calliope_mini_stubs-0.1.3.dist-info/LICENSE
calliope_mini_stubs-0.1.3.dist-info/METADATA
calliope_mini_stubs-0.1.3.dist-info/WHEEL
calliope_mini_stubs-0.1.3.dist-info/top_level.txt
calliope_mini_stubs-0.1.3.dist-info/RECORD
