Metadata-Version: 2.1
Name: calliope-mini-stubs
Version: 0.1.3
Summary: Provide stubs with documentation for MicroPython running on Calliope Mini
Home-page: https://github.com/kopp/calliope-mini-stubs
Author: kopp
License: UNKNOWN
Platform: UNKNOWN
Classifier: Programming Language :: Python :: 3
Classifier: License :: OSI Approved :: MIT License
Classifier: Operating System :: OS Independent
Requires-Python: >=3.5
